pylint_ml/__init__.py
pylint_ml/checkers/__init__.py
pylint_ml/checkers/matplotlib/__init__.py
pylint_ml/checkers/matplotlib/matplotlib_parameter.py
pylint_ml/checkers/numpy/__init__.py
pylint_ml/checkers/numpy/numpy_dot.py
pylint_ml/checkers/numpy/numpy_import.py
pylint_ml/checkers/numpy/numpy_nan_comparison.py
pylint_ml/checkers/numpy/numpy_parameter.py
pylint_ml/checkers/pandas/__init__.py
pylint_ml/checkers/pandas/pandas_copy_on_write.py
pylint_ml/checkers/pandas/pandas_dataframe_bool.py
pylint_ml/checkers/pandas/pandas_dataframe_column_selection.py
pylint_ml/checkers/pandas/pandas_dataframe_empty_column.py
pylint_ml/checkers/pandas/pandas_dataframe_iterrows.py
pylint_ml/checkers/pandas/pandas_dataframe_naming.py
pylint_ml/checkers/pandas/pandas_dataframe_values.py
pylint_ml/checkers/pandas/pandas_import.py
pylint_ml/checkers/pandas/pandas_inplace.py
pylint_ml/checkers/pandas/pandas_parameter.py
pylint_ml/checkers/pandas/pandas_series_bool.py
pylint_ml/checkers/pandas/pandas_series_naming.py
pylint_ml/checkers/scipy/__init__.py
pylint_ml/checkers/scipy/scipy_import.py
pylint_ml/checkers/scipy/scipy_parameter.py
pylint_ml/checkers/sklearn/__init__.py
pylint_ml/checkers/sklearn/sklearn_import.py
pylint_ml/checkers/sklearn/sklearn_parameter.py
pylint_ml/checkers/tensorflow/__init__.py
pylint_ml/checkers/tensorflow/tensor_parameter.py
pylint_ml/checkers/tensorflow/tensorflow_import.py
pylint_ml/checkers/torch/__init__.py
pylint_ml/checkers/torch/torch_parameter.py
pylint_ml/plugin.py
pylint_ml/util/library_handler.py
pylint_ml-0.0.1.dist-info/LICENSE
pylint_ml-0.0.1.dist-info/METADATA
pylint_ml-0.0.1.dist-info/WHEEL
pylint_ml-0.0.1.dist-info/RECORD
